gdshop_db/__init__.py
gdshop_db/__main__.py
gdshop_db/application.py
gdshop_db/content/__init__.py
gdshop_db/content/models.py
gdshop_db/crm/__init__.py
gdshop_db/crm/cli.py
gdshop_db/crm/models.py
gdshop_db/db.py
gdshop_db/delivery/__init__.py
gdshop_db/delivery/models.py
gdshop_db/dialog/__init__.py
gdshop_db/dialog/models.py
gdshop_db/marketing/__init__.py
gdshop_db/marketing/models.py
gdshop_db/notion/__init__.py
gdshop_db/notion/models.py
gdshop_db/office/__init__.py
gdshop_db/office/models.py
gdshop_db/payment/__init__.py
gdshop_db/payment/models.py
gdshop_db/profile/__init__.py
gdshop_db/profile/models.py
gdshop_db/settings.py
gdshop_db/stock/__init__.py
gdshop_db/stock/models.py
gdshop_db-0.1.1.dist-info/METADATA
gdshop_db-0.1.1.dist-info/WHEEL
gdshop_db-0.1.1.dist-info/entry_points.txt
gdshop_db-0.1.1.dist-info/RECORD
