Metadata-Version: 2.1
Name: gdshop-db
Version: 0.1.1
Summary: Grey Dream DB contracts
Home-page: https://github.com/p141592
License: MIT
Author: Nikolay Baryshnikov
Author-email: root@k0d.ru
Requires-Python: >=3.10,<4.0
Classifier: Development Status :: 3 - Alpha
Classifier: Intended Audience :: Developers
Classifier: Intended Audience :: Information Technology
Classifier: License :: OSI Approved :: MIT License
Classifier: Natural Language :: English
Classifier: Natural Language :: Russian
Classifier: Programming Language :: Python :: 3
Classifier: Programming Language :: Python :: 3.10
Classifier: Programming Language :: Python :: 3.11
Requires-Dist: alembic (>=1.12.0,<2.0.0)
Requires-Dist: psycopg2-binary (>=2.9.8,<3.0.0)
Requires-Dist: pydantic (>=2.4.2,<3.0.0)
Requires-Dist: pydantic-settings (>=2.0.3,<3.0.0)
Requires-Dist: sqlalchemy (>=2.0.21,<3.0.0)
Requires-Dist: typer (>=0.9.0,<0.10.0)
Project-URL: Repository, https://github.com/gdhorseshop/gdlib
